{
	"configurations" : 
	[
		{
			"directories" : 
			[
				{
					"build" : ".",
					"childIndexes" : 
					[
						1,
						5
					],
					"hasInstallRule" : true,
					"minimumCMakeVersion" : 
					{
						"string" : "3.0.0"
					},
					"projectIndex" : 0,
					"source" : ".",
					"targetIndexes" : 
					[
						0,
						1,
						2,
						3,
						4,
						5,
						6,
						7,
						8,
						9,
						10,
						11,
						12,
						13,
						14,
						15,
						16,
						17,
						18,
						19,
						20,
						21,
						22,
						23,
						24,
						25,
						26,
						27
					]
				},
				{
					"build" : "test",
					"childIndexes" : 
					[
						2
					],
					"hasInstallRule" : true,
					"minimumCMakeVersion" : 
					{
						"string" : "3.0.0"
					},
					"parentIndex" : 0,
					"projectIndex" : 1,
					"source" : "test",
					"targetIndexes" : 
					[
						33
					]
				},
				{
					"build" : "test/googletest",
					"childIndexes" : 
					[
						3
					],
					"hasInstallRule" : true,
					"minimumCMakeVersion" : 
					{
						"string" : "3.0.0"
					},
					"parentIndex" : 1,
					"projectIndex" : 2,
					"source" : "test/googletest"
				},
				{
					"build" : "test/googletest/googlemock",
					"childIndexes" : 
					[
						4
					],
					"hasInstallRule" : true,
					"minimumCMakeVersion" : 
					{
						"string" : "3.0.0"
					},
					"parentIndex" : 2,
					"projectIndex" : 3,
					"source" : "test/googletest/googlemock",
					"targetIndexes" : 
					[
						28,
						29
					]
				},
				{
					"build" : "test/googletest/googletest",
					"hasInstallRule" : true,
					"minimumCMakeVersion" : 
					{
						"string" : "3.0.0"
					},
					"parentIndex" : 3,
					"projectIndex" : 4,
					"source" : "test/googletest/googletest",
					"targetIndexes" : 
					[
						30,
						31
					]
				},
				{
					"build" : "sample",
					"minimumCMakeVersion" : 
					{
						"string" : "3.0.0"
					},
					"parentIndex" : 0,
					"projectIndex" : 5,
					"source" : "sample",
					"targetIndexes" : 
					[
						32
					]
				}
			],
			"name" : "Debug",
			"projects" : 
			[
				{
					"childIndexes" : 
					[
						1,
						5
					],
					"directoryIndexes" : 
					[
						0
					],
					"name" : "typeless",
					"targetIndexes" : 
					[
						0,
						1,
						2,
						3,
						4,
						5,
						6,
						7,
						8,
						9,
						10,
						11,
						12,
						13,
						14,
						15,
						16,
						17,
						18,
						19,
						20,
						21,
						22,
						23,
						24,
						25,
						26,
						27
					]
				},
				{
					"childIndexes" : 
					[
						2
					],
					"directoryIndexes" : 
					[
						1
					],
					"name" : "typeless_test",
					"parentIndex" : 0,
					"targetIndexes" : 
					[
						33
					]
				},
				{
					"childIndexes" : 
					[
						3
					],
					"directoryIndexes" : 
					[
						2
					],
					"name" : "googletest-distribution",
					"parentIndex" : 1
				},
				{
					"childIndexes" : 
					[
						4
					],
					"directoryIndexes" : 
					[
						3
					],
					"name" : "gmock",
					"parentIndex" : 2,
					"targetIndexes" : 
					[
						28,
						29
					]
				},
				{
					"directoryIndexes" : 
					[
						4
					],
					"name" : "gtest",
					"parentIndex" : 3,
					"targetIndexes" : 
					[
						30,
						31
					]
				},
				{
					"directoryIndexes" : 
					[
						5
					],
					"name" : "typeless_sample",
					"parentIndex" : 0,
					"targetIndexes" : 
					[
						32
					]
				}
			],
			"targets" : 
			[
				{
					"directoryIndex" : 0,
					"id" : "Continuous::@6890427a1f51a3e7e1df",
					"jsonFile" : "target-Continuous-Debug-e6044928ee791f2df427.json",
					"name" : "Continuous",
					"projectIndex" : 0
				},
				{
					"directoryIndex" : 0,
					"id" : "ContinuousBuild::@6890427a1f51a3e7e1df",
					"jsonFile" : "target-ContinuousBuild-Debug-32c855b6b98bdc8c5399.json",
					"name" : "ContinuousBuild",
					"projectIndex" : 0
				},
				{
					"directoryIndex" : 0,
					"id" : "ContinuousConfigure::@6890427a1f51a3e7e1df",
					"jsonFile" : "target-ContinuousConfigure-Debug-ca49d18daa39b5dd3990.json",
					"name" : "ContinuousConfigure",
					"projectIndex" : 0
				},
				{
					"directoryIndex" : 0,
					"id" : "ContinuousCoverage::@6890427a1f51a3e7e1df",
					"jsonFile" : "target-ContinuousCoverage-Debug-6a8634b01c073c99ec3a.json",
					"name" : "ContinuousCoverage",
					"projectIndex" : 0
				},
				{
					"directoryIndex" : 0,
					"id" : "ContinuousMemCheck::@6890427a1f51a3e7e1df",
					"jsonFile" : "target-ContinuousMemCheck-Debug-f1844b3ba29688bbceee.json",
					"name" : "ContinuousMemCheck",
					"projectIndex" : 0
				},
				{
					"directoryIndex" : 0,
					"id" : "ContinuousStart::@6890427a1f51a3e7e1df",
					"jsonFile" : "target-ContinuousStart-Debug-24a7942621896454f6e8.json",
					"name" : "ContinuousStart",
					"projectIndex" : 0
				},
				{
					"directoryIndex" : 0,
					"id" : "ContinuousSubmit::@6890427a1f51a3e7e1df",
					"jsonFile" : "target-ContinuousSubmit-Debug-8765820245dbd8bb144c.json",
					"name" : "ContinuousSubmit",
					"projectIndex" : 0
				},
				{
					"directoryIndex" : 0,
					"id" : "ContinuousTest::@6890427a1f51a3e7e1df",
					"jsonFile" : "target-ContinuousTest-Debug-26fb2bb09ac5cbd3c66c.json",
					"name" : "ContinuousTest",
					"projectIndex" : 0
				},
				{
					"directoryIndex" : 0,
					"id" : "ContinuousUpdate::@6890427a1f51a3e7e1df",
					"jsonFile" : "target-ContinuousUpdate-Debug-db5e0852d3d6e6d773f6.json",
					"name" : "ContinuousUpdate",
					"projectIndex" : 0
				},
				{
					"directoryIndex" : 0,
					"id" : "Experimental::@6890427a1f51a3e7e1df",
					"jsonFile" : "target-Experimental-Debug-34d31d93869b238c51bd.json",
					"name" : "Experimental",
					"projectIndex" : 0
				},
				{
					"directoryIndex" : 0,
					"id" : "ExperimentalBuild::@6890427a1f51a3e7e1df",
					"jsonFile" : "target-ExperimentalBuild-Debug-02fcaebc0d14b597f4c7.json",
					"name" : "ExperimentalBuild",
					"projectIndex" : 0
				},
				{
					"directoryIndex" : 0,
					"id" : "ExperimentalConfigure::@6890427a1f51a3e7e1df",
					"jsonFile" : "target-ExperimentalConfigure-Debug-ff5398fe1f5d046f8494.json",
					"name" : "ExperimentalConfigure",
					"projectIndex" : 0
				},
				{
					"directoryIndex" : 0,
					"id" : "ExperimentalCoverage::@6890427a1f51a3e7e1df",
					"jsonFile" : "target-ExperimentalCoverage-Debug-3b16cb1455ac2f5ca5ac.json",
					"name" : "ExperimentalCoverage",
					"projectIndex" : 0
				},
				{
					"directoryIndex" : 0,
					"id" : "ExperimentalMemCheck::@6890427a1f51a3e7e1df",
					"jsonFile" : "target-ExperimentalMemCheck-Debug-e8dcfaf550fd7e9f5a8d.json",
					"name" : "ExperimentalMemCheck",
					"projectIndex" : 0
				},
				{
					"directoryIndex" : 0,
					"id" : "ExperimentalStart::@6890427a1f51a3e7e1df",
					"jsonFile" : "target-ExperimentalStart-Debug-6f5a5c091685dcea1c7e.json",
					"name" : "ExperimentalStart",
					"projectIndex" : 0
				},
				{
					"directoryIndex" : 0,
					"id" : "ExperimentalSubmit::@6890427a1f51a3e7e1df",
					"jsonFile" : "target-ExperimentalSubmit-Debug-25397670387dcb29296f.json",
					"name" : "ExperimentalSubmit",
					"projectIndex" : 0
				},
				{
					"directoryIndex" : 0,
					"id" : "ExperimentalTest::@6890427a1f51a3e7e1df",
					"jsonFile" : "target-ExperimentalTest-Debug-d61f74ca59824ba88894.json",
					"name" : "ExperimentalTest",
					"projectIndex" : 0
				},
				{
					"directoryIndex" : 0,
					"id" : "ExperimentalUpdate::@6890427a1f51a3e7e1df",
					"jsonFile" : "target-ExperimentalUpdate-Debug-0e4665db29fd208b156d.json",
					"name" : "ExperimentalUpdate",
					"projectIndex" : 0
				},
				{
					"directoryIndex" : 0,
					"id" : "Nightly::@6890427a1f51a3e7e1df",
					"jsonFile" : "target-Nightly-Debug-e26c201f78dee67a86b7.json",
					"name" : "Nightly",
					"projectIndex" : 0
				},
				{
					"directoryIndex" : 0,
					"id" : "NightlyBuild::@6890427a1f51a3e7e1df",
					"jsonFile" : "target-NightlyBuild-Debug-5a83bf0fc17c0913fc93.json",
					"name" : "NightlyBuild",
					"projectIndex" : 0
				},
				{
					"directoryIndex" : 0,
					"id" : "NightlyConfigure::@6890427a1f51a3e7e1df",
					"jsonFile" : "target-NightlyConfigure-Debug-329abc58356b2b40f484.json",
					"name" : "NightlyConfigure",
					"projectIndex" : 0
				},
				{
					"directoryIndex" : 0,
					"id" : "NightlyCoverage::@6890427a1f51a3e7e1df",
					"jsonFile" : "target-NightlyCoverage-Debug-e096ec3043571c6fc9c8.json",
					"name" : "NightlyCoverage",
					"projectIndex" : 0
				},
				{
					"directoryIndex" : 0,
					"id" : "NightlyMemCheck::@6890427a1f51a3e7e1df",
					"jsonFile" : "target-NightlyMemCheck-Debug-27c0dc483173dd1ec875.json",
					"name" : "NightlyMemCheck",
					"projectIndex" : 0
				},
				{
					"directoryIndex" : 0,
					"id" : "NightlyMemoryCheck::@6890427a1f51a3e7e1df",
					"jsonFile" : "target-NightlyMemoryCheck-Debug-81fd5de35e2df15571c0.json",
					"name" : "NightlyMemoryCheck",
					"projectIndex" : 0
				},
				{
					"directoryIndex" : 0,
					"id" : "NightlyStart::@6890427a1f51a3e7e1df",
					"jsonFile" : "target-NightlyStart-Debug-2d1d2c3b652cdd2dd52a.json",
					"name" : "NightlyStart",
					"projectIndex" : 0
				},
				{
					"directoryIndex" : 0,
					"id" : "NightlySubmit::@6890427a1f51a3e7e1df",
					"jsonFile" : "target-NightlySubmit-Debug-6d59e68879aae04fdb73.json",
					"name" : "NightlySubmit",
					"projectIndex" : 0
				},
				{
					"directoryIndex" : 0,
					"id" : "NightlyTest::@6890427a1f51a3e7e1df",
					"jsonFile" : "target-NightlyTest-Debug-593f02e052c8bf10ffff.json",
					"name" : "NightlyTest",
					"projectIndex" : 0
				},
				{
					"directoryIndex" : 0,
					"id" : "NightlyUpdate::@6890427a1f51a3e7e1df",
					"jsonFile" : "target-NightlyUpdate-Debug-ffe537fb304d6d56172c.json",
					"name" : "NightlyUpdate",
					"projectIndex" : 0
				},
				{
					"directoryIndex" : 3,
					"id" : "gmock::@58e68f9ebf37c5473ec5",
					"jsonFile" : "target-gmock-Debug-7a0416f4203d6364fd51.json",
					"name" : "gmock",
					"projectIndex" : 3
				},
				{
					"directoryIndex" : 3,
					"id" : "gmock_main::@58e68f9ebf37c5473ec5",
					"jsonFile" : "target-gmock_main-Debug-50192a8dc84f48f69d91.json",
					"name" : "gmock_main",
					"projectIndex" : 3
				},
				{
					"directoryIndex" : 4,
					"id" : "gtest::@0c41a4af7da23b8d478e",
					"jsonFile" : "target-gtest-Debug-62a35bda89f1807836d3.json",
					"name" : "gtest",
					"projectIndex" : 4
				},
				{
					"directoryIndex" : 4,
					"id" : "gtest_main::@0c41a4af7da23b8d478e",
					"jsonFile" : "target-gtest_main-Debug-47d0f07be5115aa5451d.json",
					"name" : "gtest_main",
					"projectIndex" : 4
				},
				{
					"directoryIndex" : 5,
					"id" : "typeless_sample::@f68f564e181663381ef6",
					"jsonFile" : "target-typeless_sample-Debug-0353f22f5271f1c0c146.json",
					"name" : "typeless_sample",
					"projectIndex" : 5
				},
				{
					"directoryIndex" : 1,
					"id" : "typeless_test::@36f028580bb02cc8272a",
					"jsonFile" : "target-typeless_test-Debug-9feff5e79c2ffde9230b.json",
					"name" : "typeless_test",
					"projectIndex" : 1
				}
			]
		}
	],
	"kind" : "codemodel",
	"paths" : 
	{
		"build" : "C:/Projects/Typeless/build",
		"source" : "C:/Projects/Typeless"
	},
	"version" : 
	{
		"major" : 2,
		"minor" : 2
	}
}
